<HR>

  <TABLE cellSpacing="0" cellPadding="0" width="99%" border="0">
    <THEAD id="mainThead">
      <TR>
        <TD>
          <SPAN>
            HANSEN, Walt A <B>DOB:</B> 03/10/1962 (59 yo M) <B>Acc No.</B> 697928 <B>DOS:</B> 06/07/2021
          </SPAN>
        </TD>
      </TR>
    </THEAD>
    <TBODY>
      <TR>
        <TD>
          <TABLE cellSpacing="0" cellPadding="0" width="100%">
            <TBODY>
              <TR class="PtHeading">
                <TH rowSpan="6">
                  <IMG id="logo" alt="" src="/mobiledoc/jsp/catalog/xml/logo.JPG" width="300" height="100">
                </TH>
                <TD align="right">
                  <B>Hansen, Walt A</B>
                </TD>
              </TR>
              <TR class="PtData">
                <TD align="right">59 Y&nbsp; old &nbsp;Male,&nbsp;DOB: 03/10/1962</TD>
              </TR>
              <TR class="PtData">
                <TD align="right">Account Number:&nbsp;697928</TD>
              </TR>
              <TR class="PtData">
                <TD align="right">6340 W OVERLAND RD, MERIDIAN, ID-83642-6416</TD>
              </TR>
              <TR class="PtData">
                <TD align="right">Home: 208-284-7625&nbsp;&nbsp;&nbsp; </TD>
              </TR>
              <TR class="PtData">
                <TD align="right">Guarantor:&nbsp;Hansen, Walt A&nbsp;&nbsp;&nbsp; Insurance:&nbsp;SELECTHEALTH COMMERCIAL (LUKES)</TD>
              </TR>
              <TR class="PtData">
                <TD colSpan="2" align="right">PCP:&nbsp;Jeremy D Frix</TD>
              </TR>
              <TR class="PtData">
                <TD colSpan="2" align="right">Appointment Facility:&nbsp;MERIDIAN UC</TD>
              </TR>
            </TBODY>
          </TABLE>
          <HR>

            <TABLE cellSpacing="0" cellPadding="0" width="100%">
              <TBODY>
                <TR>
                  <TD class="PageHeader" align="left">06/07/2021</TD>
                  <TD class="PageHeader" align="right">Progress Note:&nbsp; Patrick C Denning, PA</TD>
                </TR>
              </TBODY>
            </TABLE>
            <TABLE cellSpacing="0" cellPadding="0" width="100%">
              <TBODY>
                <TR height="20">
                  <TD></TD>
                </TR>
              </TBODY>
            </TABLE>
            <TABLE cellSpacing="0" cellPadding="0" width="100%">
              <TBODY>
                <TR>
                  <TD width="100%">
                    <TABLE height="100%" cellSpacing="8" cellPadding="0" width="100%" align="left" border="0">
                      <TBODY>
                        <TR>
                          <TD vAlign="top">
                            <TABLE cellSpacing="0" cellPadding="0" width="100%">
                              <TBODY>
                                <TR class="rightPaneHeading">
                                  <TD>
                                    <B>Reason for Appointment</B>
                                  </TD>
                                </TR>
                                <TR class="rightPaneData">
                                  <TD>
                                    <TABLE class="rightPaneData" cellSpacing="0" cellPadding="0">
                                      <TBODY>
                                        <TR>
                                          <TD>1.&nbsp;L knee pain for the past two months, NKI.</TD>
                                        </TR>
                                      </TBODY>
                                    </TABLE>
                                  </TD>
                                </TR>
                              </TBODY>
                            </TABLE>
                          </TD>
                        </TR>
                        <TR>
                          <TD vAlign="top">
                            <TABLE cellSpacing="0" cellPadding="0" width="100%">
                              <TBODY>
                                <TR class="rightPaneHeading">
                                  <TD>
                                    <B>History of Present Illness</B>
                                  </TD>
                                </TR>
                                <TR class="rightPaneData">
                                  <TD>
                                    <U>LBP/Lower Extremity</U>:&nbsp; <BR>
                                      &nbsp;&nbsp;&nbsp;&nbsp;&nbsp;&nbsp; 59 year old male presents with c/o Knee Pain.&nbsp;<BR>
                                        &nbsp;&nbsp;&nbsp;&nbsp;&nbsp;&nbsp; Denies : Low Back Pain.&nbsp;<BR>
                                          &nbsp;&nbsp;&nbsp;&nbsp;&nbsp;&nbsp; Denies : Hip Pain.&nbsp;<BR>
                                            &nbsp;&nbsp;&nbsp;&nbsp;&nbsp;&nbsp; Denies : Leg Pain.&nbsp;<BR>
                                              &nbsp;&nbsp;&nbsp;&nbsp;&nbsp;&nbsp; Denies : Ankle/foot pain.&nbsp;<BR>
                                                &nbsp;&nbsp;&nbsp;&nbsp;&nbsp;&nbsp; Denies : Toe pain.&nbsp;<BR>
                                                  &nbsp;&nbsp;&nbsp;&nbsp;&nbsp;&nbsp; Denies : Acute Injury.&nbsp;<BR>
                                                    &nbsp;&nbsp;&nbsp;&nbsp;&nbsp;&nbsp; Denies : past symptoms.&nbsp;<BR>
                                                      &nbsp;&nbsp;&nbsp;&nbsp;&nbsp;&nbsp; Denies : Sprain/Twist.&nbsp;<BR>&nbsp;&nbsp;&nbsp;&nbsp;&nbsp;&nbsp; This is a 59-year-old male presents to clinic for left knee pain times 2-3 months. No known injury. Symptoms came on gradually. Patient states he has knee pain most days of the week. He has intermittent swelling and stiffness. Bending down past 90 degrees worsen his pain. Patient is a barber, he spends most the day on his feet but this does not tend to bother him too much. He notes at 1 point, he jumped into his truck and this certainly exacerbated his pain. Otherwise he describes the pain is constant, achy, mostly internally pain. As noted above, symptoms has intermittent stiffness and swelling. He has tried ice on several occasions. Otherwise treatments include none. He denies any past history of knee issues or knee injuries. Denies any acute knee pain today.
                                  </TD>
                                </TR>
                              </TBODY>
                            </TABLE>
                          </TD>
                        </TR>
                        <TR>
                          <TD vAlign="top">
                            <TABLE cellSpacing="0" cellPadding="0" width="100%" border="0">
                              <TBODY>
                                <TR class="leftPaneHeading">
                                  <TD>
                                    <B>Current Medications</B>
                                  </TD>
                                </TR>
                                <TR class="leftPaneData">
                                  <TD>
                                    <SPAN style="FONT-WEIGHT: bold; PADDING-BOTTOM: 0px; PADDING-TOP: 0px; PADDING-LEFT: 0px; PADDING-RIGHT: 0px">Taking</SPAN>
                                    <TABLE class="leftPaneData" cellSpacing="0" cellPadding="0">
                                      <TBODY>
                                        <TR>
                                          <TD>
                                            <LI>aspirin 81 mg delayed release tablet 1 tab(s) orally once a day </LI>
                                          </TD>
                                        </TR>
                                      </TBODY>
                                    </TABLE>
                                    <TABLE class="leftPaneData" cellSpacing="0" cellPadding="0">
                                      <TBODY>
                                        <TR>
                                          <TD>
                                            <LI>multivitamin Multiple Vitamins tablet 1 tab(s) orally once a day </LI>
                                          </TD>
                                        </TR>
                                      </TBODY>
                                    </TABLE>
                                    <TABLE class="leftPaneData" cellSpacing="0" cellPadding="0">
                                      <TBODY>
                                        <TR>
                                          <TD>
                                            <LI>glucosamine 500 mg capsule 1 cap(s) orally once a day </LI>
                                          </TD>
                                        </TR>
                                      </TBODY>
                                    </TABLE>
                                    <TABLE class="leftPaneData" cellSpacing="0" cellPadding="0">
                                      <TBODY>
                                        <TR>
                                          <TD>
                                            <LI>Fish oil 1000 mg po 2 bid </LI>
                                          </TD>
                                        </TR>
                                      </TBODY>
                                    </TABLE>
                                    <TABLE class="leftPaneData" cellSpacing="0" cellPadding="0">
                                      <TBODY>
                                        <TR>
                                          <TD>
                                            <LI>Vitamin C 500 mg tablet 1 tab(s) orally once a day </LI>
                                          </TD>
                                        </TR>
                                      </TBODY>
                                    </TABLE>
                                    <TABLE class="leftPaneData" cellSpacing="0" cellPadding="0">
                                      <TBODY>
                                        <TR>
                                          <TD>
                                            <LI>Levothyroxine Sodium 100 mcg (0.1 mg) tablet TAKE 1 TABLET BY MOUTH ONCE DAILY </LI>
                                          </TD>
                                        </TR>
                                      </TBODY>
                                    </TABLE>
                                    <SPAN style="FONT-WEIGHT: bold; PADDING-BOTTOM: 0px; PADDING-TOP: 0px; PADDING-LEFT: 0px; PADDING-RIGHT: 0px">Not-Taking/PRN</SPAN>
                                    <TABLE class="leftPaneData" cellSpacing="0" cellPadding="0">
                                      <TBODY>
                                        <TR>
                                          <TD>
                                            <LI>Vitamin D3 2000 intl units capsule 1 cap(s) orally once a day </LI>
                                          </TD>
                                        </TR>
                                      </TBODY>
                                    </TABLE>
                                    <TABLE class="leftPaneData" cellSpacing="0" cellPadding="0">
                                      <TBODY>
                                        <TR>
                                          <TD>
                                            <LI>propranolol 60MG capsule, extended release 1 cap(s) by mouth 2 times a day if needed, Notes: prn </LI>
                                          </TD>
                                        </TR>
                                      </TBODY>
                                    </TABLE>
                                    <SPAN style="FONT-WEIGHT: bold; PADDING-BOTTOM: 0px; PADDING-TOP: 0px; PADDING-LEFT: 0px; PADDING-RIGHT: 0px">Discontinued</SPAN>
                                    <TABLE class="leftPaneData" cellSpacing="0" cellPadding="0">
                                      <TBODY>
                                        <TR>
                                          <TD>
                                            <LI>Azelastine Hydrochloride Nasal 137 mcg/inh spray 2 spray(s) intranasally 2 times a day </LI>
                                          </TD>
                                        </TR>
                                      </TBODY>
                                    </TABLE>
                                    <TABLE class="leftPaneData" cellSpacing="0" cellPadding="0">
                                      <TBODY>
                                        <TR>
                                          <TD>
                                            <LI>Olopatadine Hydrochloride 665 mcg/inh spray 2 spray(s) intranasally 2 times a day, Notes: prn </LI>
                                          </TD>
                                        </TR>
                                      </TBODY>
                                    </TABLE>
                                    <TABLE class="leftPaneData" cellSpacing="0" cellPadding="0">
                                      <TBODY>
                                        <TR>
                                          <TD>
                                            <LI>Medication List reviewed and reconciled with the patient </LI>
                                          </TD>
                                        </TR>
                                      </TBODY>
                                    </TABLE>
                                  </TD>
                                </TR>
                              </TBODY>
                            </TABLE>
                          </TD>
                        </TR>
                        <TR>
                          <TD vAlign="top">
                            <TABLE cellSpacing="0" cellPadding="0">
                              <TBODY>
                                <TR class="leftPaneHeading">
                                  <TD>
                                    <B>
                                      <PROBLEMLIST xmlns:xsi="http://www.w3.org/1999/XMLSchema-instance" xmlns:xsd="http://www.w3.org/1999/XMLSchema" xmlns:SOAP-ENV="http://schemas.xmlsoap.org/soap/envelope/">Active Problem List</PROBLEMLIST>
                                    </B>
                                  </TD>
                                </TR>
                                <TR class="leftPaneData">
                                  <TD>
                                    <TABLE id="problemList" class="leftPaneData w850" cellSpacing="0" cellPadding="0">
                                      <TBODY>
                                        <TR>
                                          <TD vAlign="top" width="25%">&nbsp;&nbsp;&nbsp;&nbsp;&nbsp;F41.0</TD>
                                          <TD>
                                            Panic disorder<BR>
                                              <DIV>
                                                <DIV class="w180">
                                                  <DIV class="w85">
                                                    <B>Onset Date:</B>
                                                  </DIV>
                                                </DIV>
                                                <DIV class="w180">
                                                  <DIV class="w90">
                                                    <B>Modified On:</B>
                                                  </DIV>
                                                  <DIV class="w80">12/14/2020</DIV>
                                                </DIV>
                                              </DIV>
                                          </TD>
                                        </TR>
                                        <TR>
                                          <TD vAlign="top" width="25%">&nbsp;&nbsp;&nbsp;&nbsp;&nbsp;E03.9</TD>
                                          <TD>
                                            Hypothyroidism, unspecified type<BR>
                                              <DIV>
                                                <DIV class="w180">
                                                  <DIV class="w85">
                                                    <B>Onset Date:</B>
                                                  </DIV>
                                                </DIV>
                                                <DIV class="w180">
                                                  <DIV class="w90">
                                                    <B>Modified On:</B>
                                                  </DIV>
                                                  <DIV class="w80">12/14/2020</DIV>
                                                </DIV>
                                              </DIV>
                                          </TD>
                                        </TR>
                                        <TR>
                                          <TD vAlign="top" width="25%">&nbsp;&nbsp;&nbsp;&nbsp;&nbsp;E78.2</TD>
                                          <TD>
                                            Mixed hyperlipidemia<BR>
                                              <DIV>
                                                <DIV class="w180">
                                                  <DIV class="w85">
                                                    <B>Onset Date:</B>
                                                  </DIV>
                                                </DIV>
                                                <DIV class="w180">
                                                  <DIV class="w90">
                                                    <B>Modified On:</B>
                                                  </DIV>
                                                  <DIV class="w80">12/14/2020</DIV>
                                                </DIV>
                                              </DIV>
                                          </TD>
                                        </TR>
                                        <TR>
                                          <TD vAlign="top" width="25%">&nbsp;&nbsp;&nbsp;&nbsp;&nbsp;J31.0</TD>
                                          <TD>
                                            Rhinitis, unspecified type<BR>
                                              <DIV>
                                                <DIV class="w180">
                                                  <DIV class="w85">
                                                    <B>Onset Date:</B>
                                                  </DIV>
                                                </DIV>
                                                <DIV class="w180">
                                                  <DIV class="w90">
                                                    <B>Modified On:</B>
                                                  </DIV>
                                                  <DIV class="w80">05/26/2020</DIV>
                                                </DIV>
                                              </DIV>
                                          </TD>
                                        </TR>
                                      </TBODY>
                                    </TABLE>
                                  </TD>
                                </TR>
                              </TBODY>
                            </TABLE>
                          </TD>
                        </TR>
                        <TR>
                          <TD vAlign="top">
                            <TABLE cellSpacing="0" cellPadding="0" width="100%">
                              <TBODY>
                                <TR class="leftPaneHeading">
                                  <TD>
                                    <B>Past Medical History</B>
                                  </TD>
                                </TR>
                                <TR class="leftPaneData">
                                  <TD>
                                    <TABLE class="leftPaneData" cellSpacing="0" cellPadding="0">
                                      <TBODY>
                                        <TR>
                                          <TD>
                                            &nbsp;&nbsp;&nbsp;&nbsp;&nbsp;Hyperlipidemia.<BR>
                                          </TD>
                                        </TR>
                                      </TBODY>
                                    </TABLE>
                                    <TABLE class="leftPaneData" cellSpacing="0" cellPadding="0">
                                      <TBODY>
                                        <TR>
                                          <TD>
                                            &nbsp;&nbsp;&nbsp;&nbsp;&nbsp;Hypothyroid 6/11.<BR>
                                          </TD>
                                        </TR>
                                      </TBODY>
                                    </TABLE>
                                    <TABLE class="leftPaneData" cellSpacing="0" cellPadding="0">
                                      <TBODY>
                                        <TR>
                                          <TD>
                                            &nbsp;&nbsp;&nbsp;&nbsp;&nbsp;Hx panic disorder.<BR>
                                          </TD>
                                        </TR>
                                      </TBODY>
                                    </TABLE>
                                    <TABLE class="leftPaneData" cellSpacing="0" cellPadding="0">
                                      <TBODY>
                                        <TR>
                                          <TD>
                                            &nbsp;&nbsp;&nbsp;&nbsp;&nbsp;History of adenomatous polyp of colon.<BR>
                                          </TD>
                                        </TR>
                                      </TBODY>
                                    </TABLE>
                                    <TABLE class="leftPaneData" cellSpacing="0" cellPadding="0">
                                      <TBODY>
                                        <TR>
                                          <TD>
                                            &nbsp;&nbsp;&nbsp;&nbsp;&nbsp;Insulin resistance syndrome.<BR>
                                          </TD>
                                        </TR>
                                      </TBODY>
                                    </TABLE>
                                  </TD>
                                </TR>
                              </TBODY>
                            </TABLE>
                          </TD>
                        </TR>
                        <TR>
                          <TD vAlign="top">
                            <TABLE cellSpacing="0" cellPadding="0" width="100%">
                              <TBODY>
                                <TR class="leftPaneHeading">
                                  <TD>
                                    <B>Allergies</B>
                                  </TD>
                                </TR>
                                <TR class="leftPaneData">
                                  <TD>
                                    <TABLE class="leftPaneData" cellSpacing="0" cellPadding="0">
                                      <TBODY>
                                        <TR>
                                          <TD>penicillin: hives - Allergy</TD>
                                        </TR>
                                      </TBODY>
                                    </TABLE>
                                    <TABLE class="leftPaneData" cellSpacing="0" cellPadding="0">
                                      <TBODY>
                                        <TR>
                                          <TD>Norco: violently ill - Side Effects</TD>
                                        </TR>
                                      </TBODY>
                                    </TABLE>
                                  </TD>
                                </TR>
                              </TBODY>
                            </TABLE>
                          </TD>
                        </TR>
                        <TR>
                          <TD vAlign="top">
                            <TABLE cellSpacing="0" cellPadding="0" width="100%">
                              <TBODY>
                                <TR class="rightPaneHeading">
                                  <TD>
                                    <B>Vital Signs</B>
                                  </TD>
                                </TR>
                                <TR class="rightPaneData">
                                  <TD>
                                    Ht <B>72</B>, Wt <B>215.3</B>, BMI <FONT color=#"ff0000" size="2">
                                      <B>29.20</B>
                                    </FONT>, BP <FONT color=#"ff0000" size="2">
                                      <B>143/94</B>
                                    </FONT>, HR <B>96</B>, RR <B>16</B>, Temp <B>98.4</B>, O2 sat % <B>97</B><BR>T Adkins, RTR.
                                  </TD>
                                </TR>
                              </TBODY>
                            </TABLE>
                          </TD>
                        </TR>
                        <TR>
                          <TD vAlign="top">
                            <TABLE cellSpacing="0" cellPadding="0" width="100%">
                              <TBODY>
                                <TR class="rightPaneHeading">
                                  <TD>
                                    <B>Examination</B>
                                  </TD>
                                </TR>
                                <TR class="rightPaneData">
                                  <TD>
                                    <U>Brief Exam:</U>
                                    <BR>
                                      &nbsp;&nbsp;&nbsp;&nbsp;&nbsp;&nbsp; GENERAL APPEARANCE:&nbsp;<FONT size="2">well nourished</FONT><FONT size="2">, </FONT><FONT size="2">healthy and well appearing</FONT>.&nbsp;<BR>
                                        &nbsp;&nbsp;&nbsp;&nbsp;&nbsp;&nbsp; **HEENT:&nbsp;<FONT size="2">atraumatic, normocephalic</FONT><FONT size="2">, </FONT>.&nbsp;<BR>
                                          &nbsp;&nbsp;&nbsp;&nbsp;&nbsp;&nbsp; HEART:&nbsp;<FONT size="2">no murmur</FONT><FONT size="2">, </FONT><FONT size="2">RRR</FONT>.&nbsp;<BR>
                                            &nbsp;&nbsp;&nbsp;&nbsp;&nbsp;&nbsp; *CHEST:&nbsp;<FONT size="2">normal shape and expansion</FONT>.&nbsp;<BR>
                                              &nbsp;&nbsp;&nbsp;&nbsp;&nbsp;&nbsp; LUNGS:&nbsp;<FONT size="2">clear to auscultation bilaterally</FONT><FONT size="2">, </FONT><FONT size="2">no abnormal lung sounds</FONT>.&nbsp;<BR>
                                                &nbsp;&nbsp;&nbsp;&nbsp;&nbsp;&nbsp; SKIN:&nbsp;<FONT size="2">warm, dry</FONT>.&nbsp;<BR>
                                                  &nbsp;&nbsp;&nbsp;&nbsp;&nbsp;&nbsp; EXTREMITIES:&nbsp;<FONT size="2">normal ROM</FONT><FONT size="2">, </FONT><FONT size="2">no clubbing, no edema</FONT>.&nbsp;<BR>
                                                    &nbsp;&nbsp;&nbsp;&nbsp;&nbsp;&nbsp; **NEUROLOGIC EXAM:&nbsp;<FONT size="2">alert and oriented x 3</FONT>.&nbsp;<BR>
                                                      <U>Knee / Shin:</U>
                                                      <BR>
                                                        &nbsp;&nbsp;&nbsp;&nbsp;&nbsp;&nbsp; INSPECTION:&nbsp;<FONT size="2">no swelling or redness</FONT><FONT size="2">, </FONT><FONT size="2">no erythema on the joint</FONT><FONT size="2">, </FONT><FONT size="2">no ecchymosis</FONT>.&nbsp;<BR>
                                                          &nbsp;&nbsp;&nbsp;&nbsp;&nbsp;&nbsp; RANGE OF MOTION:&nbsp;<FONT size="2">FROM without pain</FONT>.&nbsp;<BR>
                                                            &nbsp;&nbsp;&nbsp;&nbsp;&nbsp;&nbsp; CREPITUS:&nbsp;<FONT size="2">none</FONT>.&nbsp;<BR>
                                                              &nbsp;&nbsp;&nbsp;&nbsp;&nbsp;&nbsp; PALPATION:&nbsp;<FONT size="2">no tenderness on jointlines or collateral ligaments</FONT><FONT size="2">, </FONT><FONT size="2">Negative Lachman's</FONT><FONT size="2">, </FONT><FONT size="2">Negative Anterior Drawer</FONT><FONT size="2">, </FONT><FONT size="2">no warmth</FONT>.&nbsp;<BR>
                                                                &nbsp;&nbsp;&nbsp;&nbsp;&nbsp;&nbsp; COLLATERAL LIGAMENTS:&nbsp;<FONT size="2">stable to varus and valgus stress</FONT><FONT size="2">, </FONT><FONT size="2">no pain with valgus and varus stress</FONT><FONT size="2">, </FONT><FONT size="2">no laxity with valgus or varus stress</FONT>.&nbsp;<BR>
                                                                  &nbsp;&nbsp;&nbsp;&nbsp;&nbsp;&nbsp; MCMURRAY:&nbsp;<FONT size="2">negative</FONT>.&nbsp;<BR>
                                                                    &nbsp;&nbsp;&nbsp;&nbsp;&nbsp;&nbsp; LACHMAN'S&nbsp;<FONT size="2">negative</FONT>.&nbsp;<BR>
                                                                      &nbsp;&nbsp;&nbsp;&nbsp;&nbsp;&nbsp; DRAWER TEST:&nbsp;<FONT size="2">anterior drawer</FONT><FONT size="2">, </FONT><FONT size="2">posterior drawer</FONT><FONT size="2">, </FONT><FONT size="2">negative</FONT>.&nbsp;<BR>
                                                                        &nbsp;&nbsp;&nbsp;&nbsp;&nbsp;&nbsp; PATELLOFEMORAL JOINT:&nbsp;<FONT size="2">no crepitations</FONT><FONT size="2">, </FONT><FONT size="2">negative apprehension sign</FONT>.&nbsp;<BR>
                                  </TD>
                                </TR>
                              </TBODY>
                            </TABLE>
                          </TD>
                        </TR>
                        <TR>
                          <TD vAlign="top">
                            <TABLE cellSpacing="0" cellPadding="0" width="100%">
                              <TBODY>
                                <TR class="leftPaneHeading">
                                  <TD>
                                    <B>Assessments</B>
                                  </TD>
                                </TR>
                                <TR>
                                  <TD></TD>
                                </TR>
                              </TBODY>
                            </TABLE>
                            <TABLE cellSpacing="0" cellPadding="0" width="100%">
                              <TBODY>
                                <TR class="rightPaneData">
                                  <TD>1. Left knee pain, unspecified chronicity - M25.562 (Primary)</TD>
                                </TR>
                              </TBODY>
                            </TABLE>
                            <TABLE cellSpacing="0" cellPadding="0" width="100%">
                              <TBODY>
                                <TR class="rightPaneData">
                                  <TD>2. Elevated blood pressure (not hypertension) - R03.0</TD>
                                </TR>
                              </TBODY>
                            </TABLE>
                          </TD>
                        </TR>
                        <TR>
                          <TD vAlign="top">
                            <TABLE cellSpacing="0" cellPadding="0" width="100%">
                              <TBODY>
                                <TR class="rightPaneHeading">
                                  <TD>
                                    <B>Treatment</B>
                                  </TD>
                                </TR>
                                <TR class="rightPaneData">
                                  <TD>
                                    <TABLE class="rightPaneData" cellSpacing="0" cellPadding="0" width="100%">
                                      <TBODY>
                                        <TR>
                                          <TD>
                                            <B>1.&nbsp;Left knee pain, unspecified chronicity</B>&nbsp; <BR>
                                              Notes: 59-year-old male with left knee pain for the past 2-3 months. Differential diagnosis includes arthritis, tendinitis, bursitis, ligament tear such as meniscus among others. Exam is unremarkable. X-rays are unremarkable other than mild tricompartmental degenerative changes. Recommend activity as tolerated, rice therapy for acute symptoms, rest, ice, elevation, compression as well as short course of anti-inflammatories such as ibuprofen or Aleve. Side effects discussed. This is been going on 1st 2-3 months, as noted above, exam and x-rays unremarkable. I will refer to sports medicine to further evaluate, consider further imaging or PT. all questions answered. Patient understood and agreed with plan and left the UC in stable condition.&nbsp;&nbsp; &nbsp;&nbsp;&nbsp;&nbsp;&nbsp;&nbsp;&nbsp;&nbsp; <BR>
                                                Referral To:Sports Medicine PHMG &nbsp;&nbsp; Sports Medicine<BR>
                                                  &nbsp;&nbsp;&nbsp;&nbsp;&nbsp;&nbsp;&nbsp;&nbsp;&nbsp;&nbsp;&nbsp;&nbsp;&nbsp;&nbsp;Reason:Left knee pain x 2 -3 months|2nd attempt completed 06/13<BR>
                                          </TD>
                                        </TR>
                                        <TR>
                                          <TD>
                                            <BR>
                                              <B>2.&nbsp;Elevated blood pressure (not hypertension)</B>&nbsp; <BR>
                                                Notes: <FONT style="FONT-SIZE: 9pt; FONT-FAMILY: Tahoma">Your blood pressure is elevated today. This may be related to your illness. However it is important to have this rechecked. You can come to our clinics and have this repeated in the next few weeks to see if this has improved. If it remains elevated it is important that you follow up with your pcp for treatment.</FONT>.&nbsp;&nbsp;
                                              </TD>
                                        </TR>
                                      </TBODY>
                                    </TABLE>
                                  </TD>
                                </TR>
                              </TBODY>
                            </TABLE>
                          </TD>
                        </TR>
                        <TR>
                          <TD vAlign="top"></TD>
                        </TR>
                        <TR>
                          <TD vAlign="top"></TD>
                        </TR>
                        <TR>
                          <TD vAlign="top">
                            <TABLE cellSpacing="0" cellPadding="0" width="100%">
                              <TBODY>
                                <TR class="rightPaneHeading">
                                  <TD width="10"></TD>
                                  <TD>
                                    <B>Diagnostic Imaging &nbsp;</B>
                                  </TD>
                                </TR>
                              </TBODY>
                            </TABLE>
                            <TABLE cellSpacing="0" cellPadding="0" width="100%">
                              <TBODY>
                                <TR class="rightPaneData">
                                  <TD>
                                    &nbsp;&nbsp;&nbsp;&nbsp;&nbsp; <U>Imaging: XR KNEE LEFT 4 OR MORE VIEWS</U>
                                  </TD>
                                </TR>
                                <TR class="rightPaneData">
                                  <TD></TD>
                                </TR>
                                <TR class="rightPaneData">
                                  <TD></TD>
                                </TR>
                                <TR class="rightPaneData">
                                  <TD></TD>
                                </TR>
                              </TBODY>
                            </TABLE>
                          </TD>
                        </TR>
                        <TR>
                          <TD vAlign="top">
                            <TABLE cellSpacing="0" cellPadding="0" width="100%">
                              <TBODY>
                                <TR class="rightPaneHeading">
                                  <TD>
                                    <B>Procedure Codes</B>
                                  </TD>
                                </TR>
                                <TR class="rightPaneData">
                                  <TD>
                                    <TABLE class="rightPaneData" cellSpacing="0" cellPadding="0">
                                      <TBODY>
                                        <TR>
                                          <TD>73564 XRAY KNEE 4 OR MORE VIEWS LEFT, Modifiers: LT </TD>
                                        </TR>
                                      </TBODY>
                                    </TABLE>
                                  </TD>
                                </TR>
                              </TBODY>
                            </TABLE>
                          </TD>
                        </TR>
                        <TR>
                          <TD vAlign="top">
                            <TABLE cellSpacing="0" cellPadding="0" width="100%">
                              <TBODY>
                                <TR class="rightPaneHeading">
                                  <TD>
                                    <B>Follow Up</B>
                                  </TD>
                                </TR>
                                <TR class="rightPaneData">
                                  <TD>see tx plan</TD>
                                </TR>
                              </TBODY>
                            </TABLE>
                          </TD>
                        </TR>
                        <TR height="10">
                          <TD></TD>
                        </TR>
                        <TR>
                          <TD vAlign="top">
                            <IMG id="signature" src="/mobiledoc/jsp/catalog/xml/patdenc.jpg?providerSignaturePostFix=18" width="175" height="100">
                          </TD>
                        </TR>
                        <TR height="10">
                          <TD></TD>
                        </TR>
                        <TR height="20">
                          <TD></TD>
                        </TR>
                        <TR class="PNSig">
                          <TD vAlign="top">Electronically signed by Patrick Denning , PA on 06/18/2021 at 09:55 AM MDT</TD>
                        </TR>
                        <TR class="PNSig">
                          <TD vAlign="top">Sign off status: Completed</TD>
                        </TR>
                        <TR height="40">
                          <TD></TD>
                        </TR>
                        <TR class="Facility">
                          <TD width="100%" align="center">
                            <HR>
                              <BR>
                                MERIDIAN UC<BR>
                                  1648 NW 1ST STREET<BR>
                                    MERIDIAN, ID 83642-1813<BR>
                                      Tel:&nbsp;208-888-9393<BR>
                                        Fax:&nbsp;208-888-9525<BR>
                          </TD>
                        </TR>
                      </TBODY>
                    </TABLE>
                  </TD>
                </TR>
              </TBODY>
            </TABLE>
        </TD>
      </TR>
    </TBODY>
    <TFOOT style="DISPLAY: table-footer-group">
      <TR>
        <TD>
          <BR>
            <HR>

              <TABLE cellSpacing="0" cellPadding="0" width="100%" border="0">
                <TBODY>
                  <TR class="TableFooter">
                    <BR>
                      <TD align="center">Progress Note:&nbsp;Patrick C Denning, PA&nbsp;&nbsp;&nbsp;&nbsp;06/07/2021</TD>
                  </TR>
                  <TR height="10">
                    <TD></TD>
                  </TR>
                  <TR class="eclinicalworks">
                    <TD align="center">Note generated by eClinicalWorks EMR/PM Software (www.eClinicalWorks.com)</TD>
                  </TR>
                </TBODY>
              </TABLE>
        </TD>
      </TR>
    </TFOOT>
  </TABLE>
  <SPAN id="chartLockedId" style="COLOR: white; DISPLAY: none" name="chartLockedId">true</SPAN>
